{
  "name": "flowering_azalea",
  "type": "block",
  "scores": {
    "dropped": {
      "1": [
        "Mandahaya",
        "Lukas_126",
        "Lord_HoruS"
      ],
      "107": [
        "__kreck"
      ],
      "11": [
        "Iglo"
      ],
      "16": [
        "philxpx"
      ],
      "195": [
        "Sayder13xr"
      ],
      "3": [
        "iurie"
      ],
      "70": [
        "__Iglo"
      ]
    },
    "mined": {
      "1": [
        "obvBasti",
        "leekcookie",
        "Ivenor",
        "StofftierAnabol",
        "Sayder13xr"
      ],
      "110": [
        "__kreck"
      ],
      "164": [
        "__Iglo"
      ],
      "17": [
        "SuperXXLProfi"
      ],
      "22": [
        "TrashSuperstar"
      ],
      "4": [
        "Lukas_126",
        "chaos1989"
      ],
      "42": [
        "philxpx"
      ],
      "5": [
        "santemjocko",
        "Iglo"
      ],
      "6": [
        "iurie"
      ]
    },
    "picked_up": {
      "12": [
        "santemjocko"
      ],
      "1219": [
        "iurie"
      ],
      "13": [
        "chaos1989"
      ],
      "15": [
        "Iglo"
      ],
      "16": [
        "leekcookie"
      ],
      "184": [
        "Sayder13xr"
      ],
      "189": [
        "__kreck"
      ],
      "22": [
        "SuperXXLProfi",
        "TrashSuperstar"
      ],
      "220": [
        "__Iglo"
      ],
      "38": [
        "philxpx"
      ]
    },
    "used": {
      "1": [
        "obvBasti",
        "philxpx",
        "StofftierAnabol"
      ],
      "11": [
        "TrashSuperstar"
      ],
      "13": [
        "__Iglo"
      ],
      "2": [
        "Lukas_126",
        "Iglo"
      ],
      "4": [
        "__kreck"
      ],
      "8": [
        "SuperXXLProfi"
      ]
    }
  }
}
