{
  "name": "diamond_sword",
  "type": "item",
  "scores": {
    "crafted": {
      "1": [
        "Mandahaya",
        "obvBasti",
        "chaos1989",
        "ScimMLG",
        "Ivenor",
        "KleeneEle",
        "owac",
        "egoplayer_Felix",
        "DornDasBrot",
        "Makishi25",
        "Teayo"
      ],
      "10": [
        "XeonVirus"
      ],
      "18": [
        "iurie"
      ],
      "2": [
        "SnuvomBodensatz",
        "lodoss2011",
        "minenicknick",
        "CuzimJxson",
        "SuperXXLProfi",
        "Cpt_looper",
        "nitram1572",
        "Lord_HoruS"
      ],
      "21": [
        "philxpx"
      ],
      "3": [
        "Mamuschkaz",
        "TrashSuperstar",
        "Warhazarder"
      ],
      "4": [
        "Temeraiere",
        "imabaldman",
        "Sayder13xr"
      ],
      "5": [
        "santemjocko"
      ],
      "63": [
        "leekcookie"
      ]
    },
    "dropped": {
      "1": [
        "obvBasti",
        "lodoss2011",
        "chaos1989",
        "minenicknick",
        "Ivenor",
        "egoplayer_Felix",
        "TrashSuperstar",
        "JonasderGamer",
        "Makishi25",
        "imabaldman",
        "Warhazarder",
        "Teayo"
      ],
      "11": [
        "santemjocko"
      ],
      "175": [
        "DornDasBrot"
      ],
      "18": [
        "leekcookie"
      ],
      "2": [
        "ScimMLG",
        "philxpx"
      ],
      "3": [
        "Mamuschkaz",
        "owac",
        "Temeraiere",
        "Telinnor",
        "Cpt_looper"
      ],
      "4": [
        "__kreck"
      ],
      "5": [
        "Iglo"
      ],
      "6": [
        "iurie"
      ]
    },
    "picked_up": {
      "10": [
        "lodoss2011"
      ],
      "11": [
        "SnuvomBodensatz",
        "Telinnor",
        "XeonVirus"
      ],
      "13": [
        "Cpt_looper"
      ],
      "161": [
        "leekcookie"
      ],
      "17": [
        "__kreck"
      ],
      "176": [
        "DornDasBrot"
      ],
      "34": [
        "iurie"
      ],
      "38": [
        "santemjocko"
      ],
      "8": [
        "Makishi25"
      ],
      "9": [
        "owac"
      ]
    },
    "used": {
      "11433": [
        "iurie"
      ],
      "3457": [
        "TrashSuperstar"
      ],
      "4253": [
        "santemjocko"
      ],
      "4778": [
        "SnuvomBodensatz"
      ],
      "5379": [
        "XeonVirus"
      ],
      "5706": [
        "Warhazarder"
      ],
      "58582": [
        "__kreck"
      ],
      "6028": [
        "chaos1989"
      ],
      "6833": [
        "owac"
      ],
      "76577": [
        "leekcookie"
      ]
    }
  }
}
