{
  "name": "feather",
  "type": "item",
  "scores": {
    "dropped": {
      "10": [
        "chaos1989"
      ],
      "13": [
        "Mamuschkaz"
      ],
      "144": [
        "leekcookie"
      ],
      "21": [
        "XeonVirus"
      ],
      "30": [
        "owac"
      ],
      "41": [
        "Temeraiere"
      ],
      "5": [
        "lodoss2011",
        "Ivenor"
      ],
      "6": [
        "Lord_HoruS"
      ],
      "7": [
        "TrashSuperstar"
      ],
      "8": [
        "ScimMLG",
        "Makishi25",
        "Sayder13xr"
      ]
    },
    "picked_up": {
      "101": [
        "XeonVirus"
      ],
      "1306": [
        "Warhazarder"
      ],
      "164": [
        "chaos1989"
      ],
      "222": [
        "leekcookie"
      ],
      "33": [
        "nitram1572"
      ],
      "36": [
        "Lukas_126"
      ],
      "37": [
        "owac"
      ],
      "38": [
        "iurie"
      ],
      "83": [
        "Temeraiere"
      ],
      "89": [
        "Mamuschkaz"
      ]
    }
  }
}
