{"dropped":{"1":["Warhazarder","leekcookie"],"2":["Sayder13xr","obvBasti"],"20":["owac"],"3":["imabaldman","iurie","lodoss2011"],"4":["Lord_HoruS"],"9":["santemjocko"]},"picked_up":{"177":["Telinnor"],"262":["Warhazarder"],"40":["Mamuschkaz","SnuvomBodensatz","Teayo"],"48":["Lukas_126"],"52":["chaos1989"],"62":["iurie"],"63":["Temeraiere"],"74":["owac"],"90":["Ivenor"],"95":["__kreck"]},"used":{"1":["Lukas_126","iurie","nitram1572"],"2":["JonasderGamer","Lord_HoruS"],"4":["leekcookie"],"5":["CuzimJxson","Mamuschkaz"]}}